setup.py
stsplatform/__init__.py
stsplatform/client.py
stsplatform.egg-info/PKG-INFO
stsplatform.egg-info/SOURCES.txt
stsplatform.egg-info/dependency_links.txt
stsplatform.egg-info/requires.txt
stsplatform.egg-info/top_level.txt
stsplatform/tests/__init__.py
stsplatform/tests/alltests.py