Metadata-Version: 1.1
Name: stsplatform
Version: 0.1.0
Summary: Use the SenseTecnic Systems Platform API
Home-page: https://github.com/SenseTecnic/stsplatform-lib-python
Author: Roberto Calderon
Author-email: rcalderon@sensetecnic.com
License: UNKNOWN
Platform: UNKNOWN
Classifier: Development Status :: 4 - Beta
Classifier: Environment :: Web Environment
Classifier: Intended Audience :: Developers
Classifier: Operating System :: OS Independent
Classifier: Programming Language :: Python
Classifier: Programming Language :: Python :: 2.6
Classifier: Programming Language :: Python :: 2.7
Classifier: Topic :: Software Development
